utils.py
manhattandistance-1.0.6.dist-info/LICENSE.txt
manhattandistance-1.0.6.dist-info/METADATA
manhattandistance-1.0.6.dist-info/WHEEL
manhattandistance-1.0.6.dist-info/top_level.txt
manhattandistance-1.0.6.dist-info/RECORD
