Metadata-Version: 2.1
Name: manhattandistance
Version: 1.0.6
Summary: Calculates the Manhattan Distance of two places
Home-page: http://packages.python.org/manhattandistance
Author: Dionysios Rigatos
Author-email: dion.rigatos@gmail.com
License: MIT License
Keywords: distance
Platform: UNKNOWN
Classifier: Development Status :: 5 - Production/Stable
Classifier: Intended Audience :: Education
Classifier: Operating System :: Microsoft :: Windows :: Windows 10
Classifier: License :: OSI Approved :: MIT License
Classifier: Programming Language :: Python :: 3
